mylang.pyc (Python 3.6)
[Code]
    File Name: <Inst>
    Object Name: (null)
    Arg Count: 0
    KW Only Arg Count: 0
    Locals: 1
    Stack Size: 4
    Flags: 0x00000001 (CO_OPTIMIZED)
    [Names]
    [Var Names]
        'c'
    [Free Vars]
    [Cell Vars]
    [Constants]
        1
        '<body>'
        [Code]
            File Name: <Inst>
            Object Name: (null)
            Arg Count: 1
            KW Only Arg Count: 0
            Locals: 1
            Stack Size: 1
            Flags: 0x00000041 (CO_OPTIMIZED | CO_NOFREE)
            [Names]
            [Var Names]
                'c'
            [Free Vars]
            [Cell Vars]
            [Constants]
                1
                None
            [Disassembly]
                0       LOAD_FAST               0: c
                2       NOP                     
                4       LOAD_CONST              0: 1
                6       NOP                     
                8       BINARY_ADD              
                10      RETURN_VALUE            
        '<val>'
        [Code]
            File Name: <Inst>
            Object Name: (null)
            Arg Count: 0
            KW Only Arg Count: 0
            Locals: 1
            Stack Size: 3
            Flags: 0x00000001 (CO_OPTIMIZED)
            [Names]
            [Var Names]
                'b'
            [Free Vars]
            [Cell Vars]
            [Constants]
                '<body>'
                [Code]
                    File Name: <Inst>
                    Object Name: (null)
                    Arg Count: 0
                    KW Only Arg Count: 0
                    Locals: 1
                    Stack Size: 2
                    Flags: 0x00000001 (CO_OPTIMIZED)
                    [Names]
                    [Var Names]
                        'c'
                    [Free Vars]
                    [Cell Vars]
                    [Constants]
                        0
                        1
                        '<body>'
                        '<val>'
                        [Code]
                            File Name: <Inst>
                            Object Name: (null)
                            Arg Count: 0
                            KW Only Arg Count: 0
                            Locals: 0
                            Stack Size: 1
                            Flags: 0x00000041 (CO_OPTIMIZED | CO_NOFREE)
                            [Names]
                            [Var Names]
                            [Free Vars]
                            [Cell Vars]
                            [Constants]
                                2
                            [Disassembly]
                                0       LOAD_CONST              0: 2
                                2       NOP                     
                                4       RETURN_VALUE            
                        [Code]
                            File Name: <Inst>
                            Object Name: (null)
                            Arg Count: 1
                            KW Only Arg Count: 0
                            Locals: 1
                            Stack Size: 1
                            Flags: 0x00000041 (CO_OPTIMIZED | CO_NOFREE)
                            [Names]
                            [Var Names]
                                'c'
                            [Free Vars]
                            [Cell Vars]
                            [Constants]
                                0
                                1
                                None
                            [Disassembly]
                                0       LOAD_FAST               0: c
                                2       NOP                     
                                4       POP_JUMP_IF_FALSE       20
                                6       NOP                     
                                8       LOAD_FAST               0: c
                                10      NOP                     
                                12      LOAD_CONST              1: 1
                                14      NOP                     
                                16      BINARY_ADD              
                                18      JUMP_FORWARD            12 (to 32)
                                20      NOP                     
                                22      LOAD_FAST               0: c
                                24      NOP                     
                                26      LOAD_CONST              0: 0
                                28      NOP                     
                                30      BINARY_MULTIPLY         
                                32      RETURN_VALUE            
                        None
                    [Disassembly]
                        0       LOAD_CONST              4: <CODE> (null)
                        2       LOAD_CONST              3: '<val>'
                        4       MAKE_FUNCTION           0
                        6       CALL_FUNCTION           0
                        8       LOAD_CONST              5: <CODE> (null)
                        10      LOAD_CONST              2: '<body>'
                        12      MAKE_FUNCTION           0
                        14      ROT_TWO                 
                        16      CALL_FUNCTION           1
                        18      STORE_FAST              0: c
                        20      LOAD_FAST               0: c
                        22      RETURN_VALUE            
                '<val>'
                None
                [Code]
                    File Name: <Inst>
                    Object Name: (null)
                    Arg Count: 1
                    KW Only Arg Count: 0
                    Locals: 1
                    Stack Size: 1
                    Flags: 0x00000041 (CO_OPTIMIZED | CO_NOFREE)
                    [Names]
                    [Var Names]
                        'b'
                    [Free Vars]
                    [Cell Vars]
                    [Constants]
                        None
                    [Disassembly]
                        0       LOAD_FAST               0: b
                        2       NOP                     
                        4       LOAD_FAST               0: b
                        6       NOP                     
                        8       BINARY_MULTIPLY         
                        10      RETURN_VALUE            
            [Disassembly]
                0       LOAD_CONST              1: <CODE> (null)
                2       LOAD_CONST              2: '<val>'
                4       MAKE_FUNCTION           0
                6       CALL_FUNCTION           0
                8       LOAD_CONST              4: <CODE> (null)
                10      LOAD_CONST              0: '<body>'
                12      MAKE_FUNCTION           0
                14      ROT_TWO                 
                16      CALL_FUNCTION           1
                18      STORE_FAST              0: b
                20      LOAD_FAST               0: b
                22      RETURN_VALUE            
        None
    [Disassembly]
        0       LOAD_CONST              4: <CODE> (null)
        2       LOAD_CONST              3: '<val>'
        4       MAKE_FUNCTION           0
        6       CALL_FUNCTION           0
        8       LOAD_CONST              2: <CODE> (null)
        10      LOAD_CONST              1: '<body>'
        12      MAKE_FUNCTION           0
        14      ROT_TWO                 
        16      CALL_FUNCTION           1
        18      STORE_FAST              0: c
        20      LOAD_FAST               0: c
        22      RETURN_VALUE            
